README.md
setup.py
test/test.py
tools_lib/__init__.py
tools_lib.egg-info/PKG-INFO
tools_lib.egg-info/SOURCES.txt
tools_lib.egg-info/dependency_links.txt
tools_lib.egg-info/top_level.txt