Metadata-Version: 2.1
Name: tools-lib
Version: 0.0.3
Summary: An integrative library that contains miscellaneous tools for performing various type of options.
Home-page: https://github.com/yogesh-aggarwal/tools-lib
Author: Yogesh Aggarwal
Author-email: developeryogeshgit@gmail.com
License: AGPL 3.0
Download-URL: https://raw.githubusercontent.com/yogesh-aggarwal/tools-lib/master/dist/tools_lib-0.0.3.tar.gz
Keywords: Miscellaneous tools,Useful
Platform: UNKNOWN
Classifier: Development Status :: 5 - Production/Stable
Classifier: Intended Audience :: Developers
Classifier: Programming Language :: Python :: 3
Classifier: Programming Language :: Python :: 3.4
Classifier: Programming Language :: Python :: 3.5
Classifier: Programming Language :: Python :: 3.6
Classifier: Programming Language :: Python :: 3.7
